test/__init__.py
test/test01.py
test/test02.py
test/test03.py
test/test04.py
xnrpc/__init__.py
xnrpc/client.py
xnrpc/server.py
xnrpc/subproc.py
xnrpc/common/__init__.py
xnrpc/common/log.py
xnrpc/common/thread.py
xnrpc/common/util.py
xnrpc-1.2.2.dist-info/DESCRIPTION.rst
xnrpc-1.2.2.dist-info/METADATA
xnrpc-1.2.2.dist-info/RECORD
xnrpc-1.2.2.dist-info/WHEEL
xnrpc-1.2.2.dist-info/metadata.json
xnrpc-1.2.2.dist-info/top_level.txt
